{
  "type": "members",
  "date": "2026-07-01",
  "members": [
    {
      "no": "1",
      "name": "まーがりん",
      "job": "ジェネティック",
      "join": "可"
    },
    {
      "no": "2",
      "name": "リュウ",
      "job": "シャドウチェイサー",
      "join": "可"
    },
    {
      "no": "3",
      "name": "Leco",
      "job": "シャドウチェイサー",
      "join": "可"
    },
    {
      "no": "4",
      "name": "Luxst",
      "job": "ソーサラー",
      "join": "可"
    },
    {
      "no": "5",
      "name": "ミキ",
      "job": "シャドウチェイサー",
      "join": "可"
    },
    {
      "no": "6",
      "name": "ちゃら",
      "job": "ギロチンクロス",
      "join": "可"
    },
    {
      "no": "7",
      "name": "とぴお",
      "job": "ギロチンクロス",
      "join": "可"
    },
    {
      "no": "8",
      "name": "なおと",
      "job": "ギロチンクロス",
      "join": "可"
    },
    {
      "no": "9",
      "name": "ガネット",
      "job": "ギロチンクロス",
      "join": "可"
    },
    {
      "no": "10",
      "name": "MercuriuS",
      "job": "ルーンナイト",
      "join": "可"
    },
    {
      "no": "11",
      "name": "MNB",
      "job": "レンジャー",
      "join": "可"
    },
    {
      "no": "12",
      "name": "YUKI",
      "job": "レンジャー",
      "join": "可"
    },
    {
      "no": "13",
      "name": "しょーん",
      "job": "レンジャー",
      "join": "可"
    },
    {
      "no": "14",
      "name": "ぴゅ",
      "job": "ギロチンクロス",
      "join": "可"
    },
    {
      "no": "15",
      "name": "るいもっち",
      "job": "ギロチンクロス",
      "join": "可"
    },
    {
      "no": "16",
      "name": "ガロード",
      "job": "ウォーロック",
      "join": "可"
    },
    {
      "no": "17",
      "name": "おみみX",
      "job": "修羅",
      "join": "可"
    },
    {
      "no": "18",
      "name": "ありす",
      "job": "アークビショップ",
      "join": "可"
    },
    {
      "no": "19",
      "name": "とも",
      "job": "ミンストレル",
      "join": "可"
    },
    {
      "no": "20",
      "name": "ちぇず",
      "job": "ギロチンクロス",
      "join": "可"
    },
    {
      "no": "21",
      "name": "しるふぃ",
      "job": "アークビショップ",
      "join": "可"
    },
    {
      "no": "22",
      "name": "やみ",
      "job": "アークビショップ",
      "join": "可"
    },
    {
      "no": "23",
      "name": "厨二",
      "job": "ギロチンクロス",
      "join": "可"
    },
    {
      "no": "24",
      "name": "ありんす",
      "job": "ミンストレル",
      "join": "可"
    },
    {
      "no": "25",
      "name": "mirumiru",
      "job": "アークビショップ",
      "join": "可"
    },
    {
      "no": "26",
      "name": "にゃんぽ",
      "job": "ウォーロック",
      "join": "可"
    },
    {
      "no": "27",
      "name": "あび",
      "job": "ルーンナイト",
      "join": "可"
    },
    {
      "no": "28",
      "name": "こここいこい",
      "job": "ルーンナイト",
      "join": "可"
    },
    {
      "no": "29",
      "name": "ダーシェンカ",
      "job": "レンジャー",
      "join": "可"
    },
    {
      "no": "30",
      "name": "ルディ",
      "job": "レンジャー",
      "join": "可"
    },
    {
      "no": "31",
      "name": "れいヴん",
      "job": "ギロチンクロス",
      "join": "可"
    },
    {
      "no": "32",
      "name": "カビゴン",
      "job": "ワンダラー",
      "join": "可"
    },
    {
      "no": "33",
      "name": "りゅうちゃびん",
      "job": "ウォーロック",
      "join": "可"
    },
    {
      "no": "34",
      "name": "ソシエ",
      "job": "アークビショップ",
      "join": "可"
    },
    {
      "no": "35",
      "name": "翠藍",
      "job": "ロイヤルガード",
      "join": "可"
    },
    {
      "no": "36",
      "name": "あお",
      "job": "ロイヤルガード",
      "join": "可"
    },
    {
      "no": "37",
      "name": "海原聖香",
      "job": "アークビショップ",
      "join": "可"
    },
    {
      "no": "38",
      "name": "あせび",
      "job": "ミンストレル",
      "join": "可"
    },
    {
      "no": "39",
      "name": "ぺりー",
      "job": "シャドウチェイサー",
      "join": "可"
    },
    {
      "no": "40",
      "name": "はまたろす",
      "job": "レンジャー",
      "join": "可"
    },
    {
      "no": "41",
      "name": "ティグリス",
      "job": "レンジャー",
      "join": "可"
    },
    {
      "no": "42",
      "name": "レイスンスン",
      "job": "ギロチンクロス",
      "join": "可"
    },
    {
      "no": "43",
      "name": "ライゼン",
      "job": "ギロチンクロス",
      "join": "可"
    },
    {
      "no": "44",
      "name": "yuki8451",
      "job": "アークビショップ",
      "join": "可"
    },
    {
      "no": "45",
      "name": "エイチャ",
      "job": "ジェネティック",
      "join": "可"
    },
    {
      "no": "46",
      "name": "フッキー",
      "job": "ルーンナイト",
      "join": "可"
    },
    {
      "no": "47",
      "name": "まゆちゃん",
      "job": "ワンダラー",
      "join": "可"
    },
    {
      "no": "48",
      "name": "SRAI",
      "job": "ギロチンクロス",
      "join": "可"
    },
    {
      "no": "49",
      "name": "両義",
      "job": "アークビショップ",
      "join": "可"
    },
    {
      "no": "50",
      "name": "ゆり",
      "job": "アークビショップ",
      "join": "可"
    },
    {
      "no": "51",
      "name": "わさびちゃん",
      "job": "シャドウチェイサー",
      "join": "可"
    },
    {
      "no": "52",
      "name": "ルカ",
      "job": "レンジャー",
      "join": "可"
    },
    {
      "no": "53",
      "name": "詩音",
      "job": "アークビショップ",
      "join": "可"
    },
    {
      "no": "54",
      "name": "鶏肉",
      "job": "ワンダラー",
      "join": "可"
    },
    {
      "no": "55",
      "name": "イロリ",
      "job": "アークビショップ",
      "join": "可"
    },
    {
      "no": "56",
      "name": "ジウォン",
      "job": "ロイヤルガード",
      "join": "可"
    },
    {
      "no": "57",
      "name": "川に流れる葉",
      "job": "ミンストレル",
      "join": "可"
    },
    {
      "no": "58",
      "name": "猫背のポワレ",
      "job": "ミンストレル",
      "join": "可"
    },
    {
      "no": "59",
      "name": "豚",
      "job": "レンジャー",
      "join": "可"
    },
    {
      "no": "60",
      "name": "リツ",
      "job": "ミンストレル",
      "join": "可"
    },
    {
      "no": "61",
      "name": "Ryo",
      "job": "レンジャー",
      "join": "可"
    },
    {
      "no": "62",
      "name": "すみちゃん",
      "job": "ワンダラー",
      "join": "可"
    },
    {
      "no": "63",
      "name": "ちぁい",
      "job": "レンジャー",
      "join": "可"
    },
    {
      "no": "64",
      "name": "Are",
      "job": "シャドウチェイサー",
      "join": "否"
    },
    {
      "no": "65",
      "name": "Celt",
      "job": "ウォーロック",
      "join": "可"
    },
    {
      "no": "66",
      "name": "まいひげ",
      "job": "シャドウチェイサー",
      "join": "否"
    },
    {
      "no": "67",
      "name": "国庫",
      "job": "アークビショップ",
      "join": "可"
    },
    {
      "no": "68",
      "name": "桜花いろは",
      "job": "ギロチンクロス",
      "join": "可"
    },
    {
      "no": "69",
      "name": "マリンスフィア",
      "job": "ソーサラー",
      "join": "可"
    },
    {
      "no": "70",
      "name": "SYU",
      "job": "ギロチンクロス",
      "join": "可"
    },
    {
      "no": "71",
      "name": "バニスマ",
      "job": "ギロチンクロス",
      "join": "否"
    },
    {
      "no": "72",
      "name": "神無月",
      "job": "ウォーロック",
      "join": "可"
    },
    {
      "no": "73",
      "name": "なわわ",
      "job": "アークビショップ",
      "join": "可"
    },
    {
      "no": "74",
      "name": "チックタック",
      "job": "アークビショップ",
      "join": "可"
    },
    {
      "no": "75",
      "name": "るぅ",
      "job": "ロイヤルガード",
      "join": "可"
    },
    {
      "no": "76",
      "name": "arlu",
      "job": "ウォーロック",
      "join": "可"
    },
    {
      "no": "77",
      "name": "もえ",
      "job": "アークビショップ",
      "join": "否"
    },
    {
      "no": "78",
      "name": "ミストガン",
      "job": "ミンストレル",
      "join": "可"
    },
    {
      "no": "79",
      "name": "ししる",
      "job": "アークビショップ",
      "join": "可"
    },
    {
      "no": "80",
      "name": "すいーぷ",
      "job": "レンジャー",
      "join": "可"
    },
    {
      "no": "81",
      "name": "よもち",
      "job": "アークビショップ",
      "join": "可"
    },
    {
      "no": "82",
      "name": "ミューズ",
      "job": "ワンダラー",
      "join": "否"
    },
    {
      "no": "83",
      "name": "バーキンワッパー",
      "job": "ルーンナイト",
      "join": "否"
    },
    {
      "no": "84",
      "name": "ばびさん",
      "job": "ワンダラー",
      "join": "可"
    },
    {
      "no": "85",
      "name": "みみたや",
      "job": "ワンダラー",
      "join": "可"
    },
    {
      "no": "86",
      "name": "ぴとー",
      "job": "シャドウチェイサー",
      "join": "可"
    },
    {
      "no": "87",
      "name": "かのたや",
      "job": "ジェネティック",
      "join": "可"
    },
    {
      "no": "88",
      "name": "ゆせ",
      "job": "ミンストレル",
      "join": "可"
    },
    {
      "no": "89",
      "name": "Neko",
      "job": "アークビショップ",
      "join": "可"
    },
    {
      "no": "90",
      "name": "S.レイニー",
      "job": "ギロチンクロス",
      "join": "否"
    },
    {
      "no": "91",
      "name": "鬼野馬",
      "job": "ギロチンクロス",
      "join": "可"
    },
    {
      "no": "92",
      "name": "鬼羅夢",
      "job": "ロイヤルガード",
      "join": "可"
    },
    {
      "no": "93",
      "name": "あいくん",
      "job": "アークビショップ",
      "join": "可"
    },
    {
      "no": "94",
      "name": "ややいえ",
      "job": "ワンダラー",
      "join": "可"
    },
    {
      "no": "95",
      "name": "てぃーきち",
      "job": "レンジャー",
      "join": "可"
    },
    {
      "no": "96",
      "name": "焼きプリン",
      "job": "ソーサラー",
      "join": "可"
    },
    {
      "no": "97",
      "name": "もこもこ",
      "job": "ウォーロック",
      "join": "可"
    },
    {
      "no": "98",
      "name": "",
      "job": "ルーンナイト",
      "join": "否"
    },
    {
      "no": "99",
      "name": "",
      "job": "ルーンナイト",
      "join": "否"
    },
    {
      "no": "100",
      "name": "",
      "job": "ルーンナイト",
      "join": "否"
    }
  ],
  "project": "twitter"
}